MANIFEST.in
README.md
UNLICENSE
setup.py
tests.py
micromodels/__init__.py
micromodels/fields.py
micromodels/models.py
micromodels.egg-info/PKG-INFO
micromodels.egg-info/SOURCES.txt
micromodels.egg-info/dependency_links.txt
micromodels.egg-info/top_level.txt
micromodels/packages/__init__.py
micromodels/packages/PySO8601/__init__.py
micromodels/packages/PySO8601/__version__.py
micromodels/packages/PySO8601/datetimestamps.py
micromodels/packages/PySO8601/durations.py
micromodels/packages/PySO8601/intervals.py
micromodels/packages/PySO8601/timezones.py
micromodels/packages/PySO8601/utility.py