Metadata-Version: 1.0
Name: micromodels
Version: 0.5.1
Summary: Declarative dictionary-based model classes for Python
Home-page: https://github.com/j4mie/micromodels/
Author: Jamie Matthews
Author-email: jamie.matthews@gmail.com
License: Public Domain
Platform: UNKNOWN
Classifier: Programming Language :: Python
Classifier: Development Status :: 3 - Alpha
Classifier: Intended Audience :: Developers
Classifier: License :: Public Domain
Classifier: Operating System :: OS Independent
Classifier: Topic :: Software Development :: Libraries :: Python Modules
